03_basic_concepts/system_tasks/system_tasks.v
/*System Tasks:
    $display - display stuff
    $monitor - if any of the variable changes, display all the values
    $monitoron
    $monitoroff
    $stop
    $finish
*/
//Compiler directives when used will be discussed there itself


module system_tasks;
    
    initial
        $display("Hello Verilog World!!");

    reg [4:0] var = 8;
    initial
        $display("Binary value of var is: %b",var);

    //$monitor

    reg clk = 0;
    always begin
        #10 clk = ~clk;
        var = var + 1;
    end
    initial begin
        $monitor($time, " Clk value is: %b -- var value is: %b", clk, var);

        #50 $stop; //type 'cont' in terminal to continue -- or 'finish' to finish the sim there. -- there are still many command present for debugging and all (explore them)
        #100 $finish;
    end  
    



    //let us get the graph for above vars:
    initial begin
    $dumpfile("system_tasks.vcd");
    $dumpvars(0,system_tasks);
    end
    

endmodule

03_basic_concepts/system_tasks/system_tasks.vcd
$date
	Mon May 04 10:15:46 2026
$end
$version
	Icarus Verilog
$end
$timescale
	1s
$end
$scope module system_tasks $end
$var reg 1 ! clk $end
$var reg 5 " var [4:0] $end
$upscope $end
$enddefinitions $end
$comment Show the parameter values. $end
$dumpall
$end
#0
$dumpvars
b1000 "
0!
$end
#10
b1001 "
1!
#20
b1010 "
0!
#30
b1011 "
1!
#40
b1100 "
0!
#50
b1101 "
1!
#60
b1110 "
0!
#70
b1111 "
1!
#80
b10000 "
0!
#90
b10001 "
1!
#100
b10010 "
0!
#110
b10011 "
1!
#120
b10100 "
0!
#130
b10101 "
1!
#140
b10110 "
0!
#150
b10111 "
1!
